hypy_utils/__init__.py
hypy_utils/__main__.py
hypy_utils/badblocks.html
hypy_utils/badblocks.py
hypy_utils/color_utils.py
hypy_utils/dict_utils.py
hypy_utils/downloader.py
hypy_utils/file_utils.py
hypy_utils/git_utils.py
hypy_utils/logging_utils.py
hypy_utils/nlp_utils.py
hypy_utils/request_utils.py
hypy_utils/scientific_utils.py
hypy_utils/serializer.py
hypy_utils/tqdm_utils.py
hypy_utils/zstd_utils.py
hypy_utils-1.0.29.dist-info/LICENSE
hypy_utils-1.0.29.dist-info/METADATA
hypy_utils-1.0.29.dist-info/WHEEL
hypy_utils-1.0.29.dist-info/top_level.txt
hypy_utils-1.0.29.dist-info/RECORD
