Metadata-Version: 2.1
Name: hypy_utils
Version: 1.0.29
Summary: Python utility functions for HyDEV
Home-page: https://github.com/hykilpikonna/HyPyUtils
Author: Azalea Gui
Author-email: me@hydev.org
License: MIT
Classifier: License :: OSI Approved :: MIT License
Classifier: Programming Language :: Python :: 3
Classifier: Programming Language :: Python :: 3.10
Classifier: Programming Language :: Python :: 3.11
Classifier: Programming Language :: Python :: 3.12
Classifier: Programming Language :: Python :: 3.13
License-File: LICENSE
